[
  {
    "SrNo": 79174,
    "District": "Sindhudurg",
    "Office": "KUDAL",
    "FPS_Id": " 152907100087",
    "RC_Id": " 272013060106",
    "MemberId": " 27201306010601",
    "MemberName": "SAWANT VINAYAK",
    "Gender": "Male",
    "Scheme Type": "NFSA",
    "Scheme": "PHH"
  },
  {
    "SrNo": 79175,
    "District": "Sindhudurg",
    "Office": "KUDAL",
    "FPS_Id": " 152907100087",
    "RC_Id": " 272013060106",
    "MemberId": " 27201306010603",
    "MemberName": "KEDU DHONDI KOLAPATE",
    "Gender": "Male",
    "UID": "XXXX-XXXX-6631",
    "Scheme Type": "NFSA",
    "Scheme": "PHH"
  },
  {
    "SrNo": 79176,
    "District": "Sindhudurg",
    "Office": "KUDAL",
    "FPS_Id": " 152907100087",
    "RC_Id": " 272013060106",
    "MemberId": " 27201306010607",
    "MemberName": "RUTUJA DINESH KOLAPATE",
    "Gender": "Female",
    "UID": "XXXX-XXXX-2945",
    "Scheme Type": "NFSA",
    "Scheme": "PHH"
  },
  {
    "SrNo": 79177,
    "District": "Sindhudurg",
    "Office": "KUDAL",
    "FPS_Id": " 152907100087",
    "RC_Id": " 272013077925",
    "MemberId": " 27201307792501",
    "MemberName": "PARULKAR ASHOK SUNDARRAO",
    "Gender": "Male",
    "Scheme Type": "NFSA",
    "Scheme": "PHH"
  },
  {
    "SrNo": 79178,
    "District": "Sindhudurg",
    "Office": "KUDAL",
    "FPS_Id": " 152907100087",
    "RC_Id": " 272013077925",
    "MemberId": " 27201307792503",
    "MemberName": "BALIRAM SAKHARAM KADAM",
    "Gender": "Male",
    "UID": "XXXX-XXXX-7744",
    "Scheme Type": "NFSA",
    "Scheme": "PHH"
  },
  {
    "SrNo": 79179,
    "District": "Sindhudurg",
    "Office": "KUDAL",
    "FPS_Id": " 152907100087",
    "RC_Id": " 272013087983",
    "MemberId": " 27201308798301",
    "MemberName": "SUNANDA",
    "Gender": "Female",
    "Scheme Type": "NFSA",
    "Scheme": "PHH"
  },
  {
    "SrNo": 79180,
    "District": "Sindhudurg",
    "Office": "KUDAL",
    "FPS_Id": " 152907100087",
    "RC_Id": " 272013091683",
    "MemberId": " 27201309168301",
    "MemberName": "ANANDI DHARMAJI JADHAV",
    "Gender": "Female",
    "UID": "XXXX-XXXX-0281",
    "Scheme Type": "NFSA",
    "Scheme": "AAY"
  },
  {
    "SrNo": 79181,
    "District": "Sindhudurg",
    "Office": "KUDAL",
    "FPS_Id": " 152907100087",
    "RC_Id": " 272013091683",
    "MemberId": " 27201309168304",
    "MemberName": "RAVINA ASHOK JADHAV",
    "Gender": "Female",
    "UID": "XXXX-XXXX-0178",
    "Scheme Type": "NFSA",
    "Scheme": "AAY"
  },
  {
    "SrNo": 79182,
    "District": "Sindhudurg",
    "Office": "KUDAL",
    "FPS_Id": " 152907100087",
    "RC_Id": " 272013091909",
    "MemberId": " 27201309190904",
    "MemberName": "VAISHNVI VASUDEV AAIR",
    "Gender": "Female",
    "Scheme Type": "NFSA",
    "Scheme": "PHH"
  },
  {
    "SrNo": 79183,
    "District": "Sindhudurg",
    "Office": "KUDAL",
    "FPS_Id": " 152907100087",
    "RC_Id": " 272013091910",
    "MemberId": " 27201309191002",
    "MemberName": "MUNNALI mohan TAVADE",
    "Gender": "Female",
    "Scheme Type": "NFSA",
    "Scheme": "PHH"
  },
  {
    "SrNo": 79184,
    "District": "Sindhudurg",
    "Office": "KUDAL",
    "FPS_Id": " 152907100087",
    "RC_Id": " 272013091912",
    "MemberId": " 27201309191201",
    "MemberName": "yashwant mahadev ghatkar",
    "Gender": "Male",
    "UID": "XXXX-XXXX-1956",
    "Scheme Type": "NFSA",
    "Scheme": "PHH"
  },
  {
    "SrNo": 79185,
    "District": "Sindhudurg",
    "Office": "KUDAL",
    "FPS_Id": " 152907100087",
    "RC_Id": " 272013091915",
    "MemberId": " 27201309191504",
    "MemberName": "VAISHALI ASHOK CHAVHAN",
    "Gender": "Female",
    "UID": "XXXX-XXXX-5603",
    "Scheme Type": "NFSA",
    "Scheme": "PHH"
  },
  {
    "SrNo": 79186,
    "District": "Sindhudurg",
    "Office": "KUDAL",
    "FPS_Id": " 152907100087",
    "RC_Id": " 272013091920",
    "MemberId": " 27201309192002",
    "MemberName": "LXMAN BIRU KOLEKAR",
    "Gender": "Male",
    "Scheme Type": "NFSA",
    "Scheme": "PHH"
  },
  {
    "SrNo": 79187,
    "District": "Sindhudurg",
    "Office": "KUDAL",
    "FPS_Id": " 152907100087",
    "RC_Id": " 272013091920",
    "MemberId": " 27201309192003",
    "MemberName": "TANAJI BIRU KOLEKAR",
    "Gender": "Male",
    "Scheme Type": "NFSA",
    "Scheme": "PHH"
  },
  {
    "SrNo": 79188,
    "District": "Sindhudurg",
    "Office": "KUDAL",
    "FPS_Id": " 152907100087",
    "RC_Id": " 272013091920",
    "MemberId": " 27201309192004",
    "MemberName": "DIPALI LAXMAN KOLEKAR",
    "Gender": "Female",
    "Scheme Type": "NFSA",
    "Scheme": "PHH"
  },
  {
    "SrNo": 79189,
    "District": "Sindhudurg",
    "Office": "KUDAL",
    "FPS_Id": " 152907100087",
    "RC_Id": " 272013091920",
    "MemberId": " 27201309192006",
    "MemberName": "DHIRJ LAXMAN KOLEKAR",
    "Gender": "Male",
    "Scheme Type": "NFSA",
    "Scheme": "PHH"
  },
  {
    "SrNo": 79190,
    "District": "Sindhudurg",
    "Office": "KUDAL",
    "FPS_Id": " 152907100087",
    "RC_Id": " 272013091920",
    "MemberId": " 27201309192007",
    "MemberName": "SAMIksha laxman KOLEKAR",
    "Gender": "Female",
    "Scheme Type": "NFSA",
    "Scheme": "PHH"
  },
  {
    "SrNo": 79191,
    "District": "Sindhudurg",
    "Office": "KUDAL",
    "FPS_Id": " 152907100087",
    "RC_Id": " 272013091923",
    "MemberId": " 27201309192304",
    "MemberName": "SANDESH MAHADEV TULSULKAR",
    "Gender": "Male",
    "UID": "XXXX-XXXX-1663",
    "Scheme Type": "NFSA",
    "Scheme": "PHH"
  },
  {
    "SrNo": 79192,
    "District": "Sindhudurg",
    "Office": "KUDAL",
    "FPS_Id": " 152907100087",
    "RC_Id": " 272013091923",
    "MemberId": " 27201309192305",
    "MemberName": "BHAKTI SANDESH TSULKAR",
    "Gender": "Female",
    "Scheme Type": "NFSA",
    "Scheme": "PHH"
  },
  {
    "SrNo": 79193,
    "District": "Sindhudurg",
    "Office": "KUDAL",
    "FPS_Id": " 152907100087",
    "RC_Id": " 272013091923",
    "MemberId": " 27201309192306",
    "MemberName": "RIYA RAJAN TSULKAR",
    "Gender": "Female",
    "Scheme Type": "NFSA",
    "Scheme": "PHH"
  },
  {
    "SrNo": 79194,
    "District": "Sindhudurg",
    "Office": "KUDAL",
    "FPS_Id": " 152907100087",
    "RC_Id": " 272013091923",
    "MemberId": " 27201309192307",
    "MemberName": "SHRAVANI SANDESH TULSULKAR",
    "Gender": "Female",
    "Scheme Type": "NFSA",
    "Scheme": "PHH"
  },
  {
    "SrNo": 79195,
    "District": "Sindhudurg",
    "Office": "KUDAL",
    "FPS_Id": " 152907100087",
    "RC_Id": " 272013091925",
    "MemberId": " 27201309192503",
    "MemberName": "SHIVAJI tanaji SHELAKE",
    "Gender": "Male",
    "Scheme Type": "NFSA",
    "Scheme": "PHH"
  },
  {
    "SrNo": 79196,
    "District": "Sindhudurg",
    "Office": "KUDAL",
    "FPS_Id": " 152907100087",
    "RC_Id": " 272013091929",
    "MemberId": " 27201309192903",
    "MemberName": "KRUPALI VISHRAM AAIR",
    "Gender": "Female",
    "UID": "XXXX-XXXX-0348",
    "Scheme Type": "NFSA",
    "Scheme": "PHH"
  },
  {
    "SrNo": 79197,
    "District": "Sindhudurg",
    "Office": "KUDAL",
    "FPS_Id": " 152907100087",
    "RC_Id": " 272013091929",
    "MemberId": " 27201309192904",
    "MemberName": "SAGAR VISHRAM AAIR",
    "Gender": "Male",
    "UID": "XXXX-XXXX-5506",
    "Scheme Type": "NFSA",
    "Scheme": "PHH"
  },
  {
    "SrNo": 79198,
    "District": "Sindhudurg",
    "Office": "KUDAL",
    "FPS_Id": " 152907100087",
    "RC_Id": " 272013091934",
    "MemberId": " 27201309193402",
    "MemberName": "LAKSHMI prakash MARGAJ",
    "Gender": "Female",
    "UID": "XXXX-XXXX-5682",
    "Scheme Type": "NFSA",
    "Scheme": "PHH"
  },
  {
    "SrNo": 79199,
    "District": "Sindhudurg",
    "Office": "KUDAL",
    "FPS_Id": " 152907100087",
    "RC_Id": " 272013091942",
    "MemberId": " 27201309194201",
    "MemberName": "MALU AAIR",
    "Gender": "Male",
    "UID": "XXXX-XXXX-9315",
    "Scheme Type": "NFSA",
    "Scheme": "PHH"
  },
  {
    "SrNo": 79200,
    "District": "Sindhudurg",
    "Office": "KUDAL",
    "FPS_Id": " 152907100087",
    "RC_Id": " 272013091942",
    "MemberId": " 27201309194202",
    "MemberName": "SUNITA AAIR",
    "Gender": "Female",
    "UID": "XXXX-XXXX-8367",
    "Scheme Type": "NFSA",
    "Scheme": "PHH"
  },
  {
    "SrNo": 79201,
    "District": "Sindhudurg",
    "Office": "KUDAL",
    "FPS_Id": " 152907100087",
    "RC_Id": " 272013091942",
    "MemberId": " 27201309194204",
    "MemberName": "SMITA AAIR",
    "Gender": "Female",
    "Scheme Type": "NFSA",
    "Scheme": "PHH"
  },
  {
    "SrNo": 79202,
    "District": "Sindhudurg",
    "Office": "KUDAL",
    "FPS_Id": " 152907100087",
    "RC_Id": " 272013091946",
    "MemberId": " 27201309194603",
    "MemberName": "VARSHA vasudev KADAM",
    "Gender": "Female",
    "UID": "XXXX-XXXX-5733",
    "Scheme Type": "NFSA",
    "Scheme": "PHH"
  },
  {
    "SrNo": 79203,
    "District": "Sindhudurg",
    "Office": "KUDAL",
    "FPS_Id": " 152907100087",
    "RC_Id": " 272013091950",
    "MemberId": " 27201309195002",
    "MemberName": "shashikala chandrakant marathe",
    "Gender": "Female",
    "UID": "XXXX-XXXX-2306",
    "Scheme Type": "NFSA",
    "Scheme": "PHH"
  },
  {
    "SrNo": 79204,
    "District": "Sindhudurg",
    "Office": "KUDAL",
    "FPS_Id": " 152907100087",
    "RC_Id": " 272013091953",
    "MemberId": " 27201309195301",
    "MemberName": "LAXMI PANDURANG GAWADE",
    "Gender": "Female",
    "UID": "XXXX-XXXX-2226",
    "Scheme Type": "NFSA",
    "Scheme": "PHH"
  },
  {
    "SrNo": 79205,
    "District": "Sindhudurg",
    "Office": "KUDAL",
    "FPS_Id": " 152907100087",
    "RC_Id": " 272013091953",
    "MemberId": " 27201309195303",
    "MemberName": "lavanya rakesh gawade",
    "Gender": "Female",
    "UID": "XXXX-XXXX-5500",
    "Scheme Type": "NFSA",
    "Scheme": "PHH"
  },
  {
    "SrNo": 79206,
    "District": "Sindhudurg",
    "Office": "KUDAL",
    "FPS_Id": " 152907100087",
    "RC_Id": " 272013091953",
    "MemberId": " 27201309195305",
    "MemberName": "nishtha rakesh gawade",
    "Gender": "Female",
    "UID": "XXXX-XXXX-8210",
    "Scheme Type": "NFSA",
    "Scheme": "PHH"
  },
  {
    "SrNo": 79207,
    "District": "Sindhudurg",
    "Office": "KUDAL",
    "FPS_Id": " 152907100087",
    "RC_Id": " 272013091954",
    "MemberId": " 27201309195406",
    "MemberName": "krishna chandrakant lad",
    "Gender": "Male",
    "UID": "XXXX-XXXX-7895",
    "Scheme Type": "NFSA",
    "Scheme": "PHH"
  },
  {
    "SrNo": 79208,
    "District": "Sindhudurg",
    "Office": "KUDAL",
    "FPS_Id": " 152907100087",
    "RC_Id": " 272013091955",
    "MemberId": " 27201309195501",
    "MemberName": "DHULAJI BUTE",
    "Gender": "Male",
    "Scheme Type": "NFSA",
    "Scheme": "PHH"
  },
  {
    "SrNo": 79209,
    "District": "Sindhudurg",
    "Office": "KUDAL",
    "FPS_Id": " 152907100087",
    "RC_Id": " 272013091955",
    "MemberId": " 27201309195503",
    "MemberName": "LAXMAN DHULAJI BUTE",
    "Gender": "Male",
    "UID": "XXXX-XXXX-5926",
    "Scheme Type": "NFSA",
    "Scheme": "PHH"
  },
  {
    "SrNo": 79210,
    "District": "Sindhudurg",
    "Office": "KUDAL",
    "FPS_Id": " 152907100087",
    "RC_Id": " 272013091956",
    "MemberId": " 27201309195606",
    "MemberName": "SHANTI babu SHELaKE",
    "Gender": "Male",
    "Scheme Type": "NFSA",
    "Scheme": "PHH"
  },
  {
    "SrNo": 79211,
    "District": "Sindhudurg",
    "Office": "KUDAL",
    "FPS_Id": " 152907100087",
    "RC_Id": " 272013091957",
    "MemberId": " 27201309195704",
    "MemberName": "PRIYANKA GODE",
    "Gender": "Female",
    "Scheme Type": "NFSA",
    "Scheme": "PHH"
  },
  {
    "SrNo": 79212,
    "District": "Sindhudurg",
    "Office": "KUDAL",
    "FPS_Id": " 152907100087",
    "RC_Id": " 272013091958",
    "MemberId": " 27201309195801",
    "MemberName": "MADHUKAR sitaram GOVEKAR",
    "Gender": "Male",
    "UID": "XXXX-XXXX-3692",
    "Scheme Type": "NFSA",
    "Scheme": "PHH"
  },
  {
    "SrNo": 79213,
    "District": "Sindhudurg",
    "Office": "KUDAL",
    "FPS_Id": " 152907100087",
    "RC_Id": " 272013091968",
    "MemberId": " 27201309196802",
    "MemberName": "VIJAYA bhaskar JADHAV",
    "Gender": "Female",
    "UID": "XXXX-XXXX-9176",
    "Scheme Type": "NFSA",
    "Scheme": "PHH"
  },
  {
    "SrNo": 79214,
    "District": "Sindhudurg",
    "Office": "KUDAL",
    "FPS_Id": " 152907100087",
    "RC_Id": " 272013091968",
    "MemberId": " 27201309196803",
    "MemberName": "DATTARAM bhaskar JADHAV",
    "Gender": "Male",
    "UID": "XXXX-XXXX-8475",
    "Scheme Type": "NFSA",
    "Scheme": "PHH"
  },
  {
    "SrNo": 79215,
    "District": "Sindhudurg",
    "Office": "KUDAL",
    "FPS_Id": " 152907100087",
    "RC_Id": " 272013091972",
    "MemberId": " 27201309197201",
    "MemberName": "BAMU KANU SHELaKE",
    "Gender": "Male",
    "UID": "XXXX-XXXX-4550",
    "Scheme Type": "NFSA",
    "Scheme": "PHH"
  },
  {
    "SrNo": 79216,
    "District": "Sindhudurg",
    "Office": "KUDAL",
    "FPS_Id": " 152907100087",
    "RC_Id": " 272013091973",
    "MemberId": " 27201309197301",
    "MemberName": "ASHA ANKUSH TULSULKAR",
    "Gender": "Female",
    "UID": "XXXX-XXXX-5426",
    "Scheme Type": "NFSA",
    "Scheme": "PHH"
  },
  {
    "SrNo": 79217,
    "District": "Sindhudurg",
    "Office": "KUDAL",
    "FPS_Id": " 152907100087",
    "RC_Id": " 272013091973",
    "MemberId": " 27201309197304",
    "MemberName": "TANISHKA ASHISH TULSULKAR",
    "Gender": "Female",
    "UID": "XXXX-XXXX-6099",
    "Scheme Type": "NFSA",
    "Scheme": "PHH"
  },
  {
    "SrNo": 79218,
    "District": "Sindhudurg",
    "Office": "KUDAL",
    "FPS_Id": " 152907100087",
    "RC_Id": " 272013091980",
    "MemberId": " 27201309198002",
    "MemberName": "SUDHIR GOPAL SHIRKE",
    "Gender": "Male",
    "UID": "XXXX-XXXX-0019",
    "Scheme Type": "NFSA",
    "Scheme": "AAY"
  },
  {
    "SrNo": 79219,
    "District": "Sindhudurg",
    "Office": "KUDAL",
    "FPS_Id": " 152907100087",
    "RC_Id": " 272013091983",
    "MemberId": " 27201309198301",
    "MemberName": "SULOCHNA LAXMAN GAWADE",
    "Gender": "Female",
    "UID": "XXXX-XXXX-8247",
    "Scheme Type": "NFSA",
    "Scheme": "AAY"
  },
  {
    "SrNo": 79220,
    "District": "Sindhudurg",
    "Office": "KUDAL",
    "FPS_Id": " 152907100087",
    "RC_Id": " 272013091983",
    "MemberId": " 27201309198307",
    "MemberName": "NACHIKET DATTATRAY GAWADE",
    "Gender": "Male",
    "UID": "XXXX-XXXX-2406",
    "Scheme Type": "NFSA",
    "Scheme": "AAY"
  },
  {
    "SrNo": 79221,
    "District": "Sindhudurg",
    "Office": "KUDAL",
    "FPS_Id": " 152907100087",
    "RC_Id": " 272013091987",
    "MemberId": " 27201309198701",
    "MemberName": "SHUBHANGI DASHARATH WARANG",
    "Gender": "Female",
    "UID": "XXXX-XXXX-7222",
    "Scheme Type": "NFSA",
    "Scheme": "PHH"
  },
  {
    "SrNo": 79222,
    "District": "Sindhudurg",
    "Office": "KUDAL",
    "FPS_Id": " 152907100087",
    "RC_Id": " 272013091990",
    "MemberId": " 27201309199003",
    "MemberName": "SONIYA prabhakar SAWANT",
    "Gender": "Female",
    "Scheme Type": "NFSA",
    "Scheme": "PHH"
  },
  {
    "SrNo": 79223,
    "District": "Sindhudurg",
    "Office": "KUDAL",
    "FPS_Id": " 152907100087",
    "RC_Id": " 272013092000",
    "MemberId": " 27201309200001",
    "MemberName": "SUNITA SANJAY NATEKAR",
    "Gender": "Female",
    "UID": "XXXX-XXXX-7709",
    "Scheme Type": "NFSA",
    "Scheme": "PHH"
  },
  {
    "SrNo": 79224,
    "District": "Sindhudurg",
    "Office": "KUDAL",
    "FPS_Id": " 152907100087",
    "RC_Id": " 272013092000",
    "MemberId": " 27201309200002",
    "MemberName": "LILADHAR SANJAY NATEKAR",
    "Gender": "Male",
    "UID": "XXXX-XXXX-2320",
    "Scheme Type": "NFSA",
    "Scheme": "PHH"
  },
  {
    "SrNo": 79225,
    "District": "Sindhudurg",
    "Office": "KUDAL",
    "FPS_Id": " 152907100087",
    "RC_Id": " 272013092000",
    "MemberId": " 27201309200004",
    "MemberName": "MITALI LILADHAR NATEKAR",
    "Gender": "Female",
    "UID": "XXXX-XXXX-1483",
    "Scheme Type": "NFSA",
    "Scheme": "PHH"
  },
  {
    "SrNo": 79226,
    "District": "Sindhudurg",
    "Office": "KUDAL",
    "FPS_Id": " 152907100087",
    "RC_Id": " 272013092001",
    "MemberId": " 27201309200102",
    "MemberName": "SUNIL SUBHASH JADHAV",
    "Gender": "Male",
    "UID": "XXXX-XXXX-3633",
    "Scheme Type": "NFSA",
    "Scheme": "AAY"
  },
  {
    "SrNo": 79227,
    "District": "Sindhudurg",
    "Office": "KUDAL",
    "FPS_Id": " 152907100087",
    "RC_Id": " 272013092001",
    "MemberId": " 27201309200104",
    "MemberName": "SAWALI SUNIL JADHAV",
    "Gender": "Female",
    "Scheme Type": "NFSA",
    "Scheme": "AAY"
  },
  {
    "SrNo": 79228,
    "District": "Sindhudurg",
    "Office": "KUDAL",
    "FPS_Id": " 152907100087",
    "RC_Id": " 272013092001",
    "MemberId": " 27201309200109",
    "MemberName": "LUIS ANIL JADHAV",
    "Gender": "Male",
    "UID": "XXXX-XXXX-1300",
    "Scheme Type": "NFSA",
    "Scheme": "AAY"
  },
  {
    "SrNo": 79229,
    "District": "Sindhudurg",
    "Office": "KUDAL",
    "FPS_Id": " 152907100087",
    "RC_Id": " 272013092003",
    "MemberId": " 27201309200304",
    "MemberName": "PANDURANG babali CHAVAN",
    "Gender": "Male",
    "UID": "XXXX-XXXX-0077",
    "Scheme Type": "NFSA",
    "Scheme": "AAY"
  },
  {
    "SrNo": 79230,
    "District": "Sindhudurg",
    "Office": "KUDAL",
    "FPS_Id": " 152907100087",
    "RC_Id": " 272013092006",
    "MemberId": " 27201309200602",
    "MemberName": "GURUNATH ANANT AAIR",
    "Gender": "Male",
    "UID": "XXXX-XXXX-2396",
    "Scheme Type": "NFSA",
    "Scheme": "AAY"
  },
  {
    "SrNo": 79231,
    "District": "Sindhudurg",
    "Office": "KUDAL",
    "FPS_Id": " 152907100087",
    "RC_Id": " 272013092006",
    "MemberId": " 27201309200603",
    "MemberName": "ANKITA ANANT AAIR",
    "Gender": "Female",
    "UID": "XXXX-XXXX-5774",
    "Scheme Type": "NFSA",
    "Scheme": "AAY"
  },
  {
    "SrNo": 79232,
    "District": "Sindhudurg",
    "Office": "KUDAL",
    "FPS_Id": " 152907100087",
    "RC_Id": " 272013092009",
    "MemberId": " 27201309200902",
    "MemberName": "RUPALI VISHAL PARAB",
    "Gender": "Female",
    "UID": "XXXX-XXXX-5992",
    "Scheme Type": "NFSA",
    "Scheme": "PHH"
  },
  {
    "SrNo": 79233,
    "District": "Sindhudurg",
    "Office": "KUDAL",
    "FPS_Id": " 152907100087",
    "RC_Id": " 272013092009",
    "MemberId": " 27201309200904",
    "MemberName": "VISHAL SITARAM PARAB",
    "Gender": "Male",
    "UID": "XXXX-XXXX-2489",
    "Scheme Type": "NFSA",
    "Scheme": "PHH"
  },
  {
    "SrNo": 79234,
    "District": "Sindhudurg",
    "Office": "KUDAL",
    "FPS_Id": " 152907100087",
    "RC_Id": " 272013092012",
    "MemberId": " 27201309201204",
    "MemberName": "ULHAS LAVU KARANGUTKAR",
    "Gender": "Male",
    "UID": "XXXX-XXXX-4254",
    "Scheme Type": "NFSA",
    "Scheme": "PHH"
  },
  {
    "SrNo": 79235,
    "District": "Sindhudurg",
    "Office": "KUDAL",
    "FPS_Id": " 152907100087",
    "RC_Id": " 272013092013",
    "MemberId": " 27201309201302",
    "MemberName": "SARASVATI GANPAT SAWANT",
    "Gender": "Female",
    "UID": "XXXX-XXXX-1632",
    "Scheme Type": "NFSA",
    "Scheme": "PHH"
  },
  {
    "SrNo": 79236,
    "District": "Sindhudurg",
    "Office": "KUDAL",
    "FPS_Id": " 152907100087",
    "RC_Id": " 272013092019",
    "MemberId": " 27201309201903",
    "MemberName": "VAISHALI vijay DESAI",
    "Gender": "Male",
    "Scheme Type": "NFSA",
    "Scheme": "PHH"
  },
  {
    "SrNo": 79237,
    "District": "Sindhudurg",
    "Office": "KUDAL",
    "FPS_Id": " 152907100087",
    "RC_Id": " 272013092020",
    "MemberId": " 27201309202003",
    "MemberName": "SAHILI SUBHASH TULSULKAR",
    "Gender": "Male",
    "UID": "XXXX-XXXX-0510",
    "Scheme Type": "NFSA",
    "Scheme": "PHH"
  },
  {
    "SrNo": 79238,
    "District": "Sindhudurg",
    "Office": "KUDAL",
    "FPS_Id": " 152907100087",
    "RC_Id": " 272013092020",
    "MemberId": " 27201309202005",
    "MemberName": "KOMAL SUBHASH TULSULKAR",
    "Gender": "Male",
    "UID": "XXXX-XXXX-2673",
    "Scheme Type": "NFSA",
    "Scheme": "PHH"
  },
  {
    "SrNo": 79239,
    "District": "Sindhudurg",
    "Office": "KUDAL",
    "FPS_Id": " 152907100087",
    "RC_Id": " 272013092023",
    "MemberId": " 27201309202303",
    "MemberName": "WOLTAR KAITAN MENDIS",
    "Gender": "Male",
    "Scheme Type": "NFSA",
    "Scheme": "PHH"
  },
  {
    "SrNo": 79240,
    "District": "Sindhudurg",
    "Office": "KUDAL",
    "FPS_Id": " 152907100087",
    "RC_Id": " 272013092024",
    "MemberId": " 27201309202402",
    "MemberName": "VAIBHAV AANGCHEKAR",
    "Gender": "Male",
    "UID": "XXXX-XXXX-0025",
    "Scheme Type": "NFSA",
    "Scheme": "PHH"
  },
  {
    "SrNo": 79241,
    "District": "Sindhudurg",
    "Office": "KUDAL",
    "FPS_Id": " 152907100087",
    "RC_Id": " 272013092024",
    "MemberId": " 27201309202403",
    "MemberName": "VAISHALI AANGCHEKAR",
    "Gender": "Female",
    "UID": "XXXX-XXXX-5572",
    "Scheme Type": "NFSA",
    "Scheme": "PHH"
  },
  {
    "SrNo": 79242,
    "District": "Sindhudurg",
    "Office": "KUDAL",
    "FPS_Id": " 152907100087",
    "RC_Id": " 272013092028",
    "MemberId": " 27201309202804",
    "MemberName": "SHILPA SADVELKAR",
    "Gender": "Female",
    "Scheme Type": "NFSA",
    "Scheme": "PHH"
  },
  {
    "SrNo": 79243,
    "District": "Sindhudurg",
    "Office": "KUDAL",
    "FPS_Id": " 152907100087",
    "RC_Id": " 272013092028",
    "MemberId": " 27201309202805",
    "MemberName": "SAMIR MADHUKAR SADVELKAR",
    "Gender": "Male",
    "Scheme Type": "NFSA",
    "Scheme": "PHH"
  },
  {
    "SrNo": 79244,
    "District": "Sindhudurg",
    "Office": "KUDAL",
    "FPS_Id": " 152907100087",
    "RC_Id": " 272013092029",
    "MemberId": " 27201309202901",
    "MemberName": "SHIVRAM SHANKAR GORULE",
    "Gender": "Male",
    "UID": "XXXX-XXXX-7657",
    "Scheme Type": "NFSA",
    "Scheme": "PHH"
  },
  {
    "SrNo": 79245,
    "District": "Sindhudurg",
    "Office": "KUDAL",
    "FPS_Id": " 152907100087",
    "RC_Id": " 272013092030",
    "MemberId": " 27201309203006",
    "MemberName": "MANAV SUNIL LAD",
    "Gender": "Male",
    "Scheme Type": "NFSA",
    "Scheme": "PHH"
  },
  {
    "SrNo": 79246,
    "District": "Sindhudurg",
    "Office": "KUDAL",
    "FPS_Id": " 152907100087",
    "RC_Id": " 272013092031",
    "MemberId": " 27201309203101",
    "MemberName": "RUKMINI SADVLEKAR",
    "Gender": "Female",
    "UID": "XXXX-XXXX-4816",
    "Scheme Type": "NFSA",
    "Scheme": "PHH"
  },
  {
    "SrNo": 79247,
    "District": "Sindhudurg",
    "Office": "KUDAL",
    "FPS_Id": " 152907100087",
    "RC_Id": " 272013092032",
    "MemberId": " 27201309203203",
    "MemberName": "EKNATH vasant GORULe",
    "Gender": "Male",
    "UID": "XXXX-XXXX-5653",
    "Scheme Type": "NFSA",
    "Scheme": "PHH"
  },
  {
    "SrNo": 79248,
    "District": "Sindhudurg",
    "Office": "KUDAL",
    "FPS_Id": " 152907100087",
    "RC_Id": " 272013092032",
    "MemberId": " 27201309203205",
    "MemberName": "EKANATH VASANT GORULE",
    "Gender": "Male",
    "Scheme Type": "NFSA",
    "Scheme": "PHH"
  },
  {
    "SrNo": 79249,
    "District": "Sindhudurg",
    "Office": "KUDAL",
    "FPS_Id": " 152907100087",
    "RC_Id": " 272013092032",
    "MemberId": " 27201309203206",
    "MemberName": "SAMRUDDHI EKANATH GORULE",
    "Gender": "Female",
    "Scheme Type": "NFSA",
    "Scheme": "PHH"
  },
  {
    "SrNo": 79250,
    "District": "Sindhudurg",
    "Office": "KUDAL",
    "FPS_Id": " 152907100087",
    "RC_Id": " 272013092032",
    "MemberId": " 27201309203207",
    "MemberName": "ASMITA EKNATH GORULE",
    "Gender": "Female",
    "UID": "XXXX-XXXX-6495",
    "Scheme Type": "NFSA",
    "Scheme": "PHH"
  },
  {
    "SrNo": 79251,
    "District": "Sindhudurg",
    "Office": "KUDAL",
    "FPS_Id": " 152907100087",
    "RC_Id": " 272013092036",
    "MemberId": " 27201309203602",
    "MemberName": "JANI SAGUN KOLAPATE",
    "Gender": "Female",
    "UID": "XXXX-XXXX-7648",
    "Scheme Type": "NFSA",
    "Scheme": "PHH"
  },
  {
    "SrNo": 79252,
    "District": "Sindhudurg",
    "Office": "KUDAL",
    "FPS_Id": " 152907100087",
    "RC_Id": " 272013092037",
    "MemberId": " 27201309203704",
    "MemberName": "meenakshi ragho aair",
    "Gender": "Female",
    "UID": "XXXX-XXXX-8192",
    "Scheme Type": "NFSA",
    "Scheme": "PHH"
  },
  {
    "SrNo": 79253,
    "District": "Sindhudurg",
    "Office": "KUDAL",
    "FPS_Id": " 152907100087",
    "RC_Id": " 272013092038",
    "MemberId": " 27201309203803",
    "MemberName": "SANGITA SHAHU VARAK",
    "Gender": "Female",
    "Scheme Type": "NFSA",
    "Scheme": "PHH"
  },
  {
    "SrNo": 79254,
    "District": "Sindhudurg",
    "Office": "KUDAL",
    "FPS_Id": " 152907100087",
    "RC_Id": " 272013092038",
    "MemberId": " 27201309203807",
    "MemberName": "ANANYA BABAN VARAK",
    "Gender": "Female",
    "Scheme Type": "NFSA",
    "Scheme": "PHH"
  },
  {
    "SrNo": 79255,
    "District": "Sindhudurg",
    "Office": "KUDAL",
    "FPS_Id": " 152907100087",
    "RC_Id": " 272013092041",
    "MemberId": " 27201309204102",
    "MemberName": "PRATIBHA BIRMOLE",
    "Gender": "Female",
    "UID": "XXXX-XXXX-0555",
    "Scheme Type": "NFSA",
    "Scheme": "PHH"
  },
  {
    "SrNo": 79256,
    "District": "Sindhudurg",
    "Office": "KUDAL",
    "FPS_Id": " 152907100087",
    "RC_Id": " 272013092041",
    "MemberId": " 27201309204103",
    "MemberName": "PRATHIBHA prabhakar BIRMOLE",
    "Gender": "Female",
    "Scheme Type": "NFSA",
    "Scheme": "PHH"
  },
  {
    "SrNo": 79257,
    "District": "Sindhudurg",
    "Office": "KUDAL",
    "FPS_Id": " 152907100087",
    "RC_Id": " 272013092042",
    "MemberId": " 27201309204201",
    "MemberName": "VASANT SAWANT",
    "Gender": "Male",
    "UID": "XXXX-XXXX-3136",
    "Scheme Type": "NFSA",
    "Scheme": "PHH"
  },
  {
    "SrNo": 79258,
    "District": "Sindhudurg",
    "Office": "KUDAL",
    "FPS_Id": " 152907100087",
    "RC_Id": " 272013092045",
    "MemberId": " 27201309204501",
    "MemberName": "GOPIKA govind SADVELKAR",
    "Gender": "Female",
    "UID": "XXXX-XXXX-7128",
    "Scheme Type": "NFSA",
    "Scheme": "PHH"
  },
  {
    "SrNo": 79259,
    "District": "Sindhudurg",
    "Office": "KUDAL",
    "FPS_Id": " 152907100087",
    "RC_Id": " 272013092045",
    "MemberId": " 27201309204502",
    "MemberName": "SUSHAMA govind SADVELKAR",
    "Gender": "Female",
    "Scheme Type": "NFSA",
    "Scheme": "PHH"
  },
  {
    "SrNo": 79260,
    "District": "Sindhudurg",
    "Office": "KUDAL",
    "FPS_Id": " 152907100087",
    "RC_Id": " 272013092051",
    "MemberId": " 27201309205107",
    "MemberName": "ATHARV PRADIP AAIR",
    "Gender": "Male",
    "UID": "XXXX-XXXX-2650",
    "Scheme Type": "NFSA",
    "Scheme": "PHH"
  },
  {
    "SrNo": 79261,
    "District": "Sindhudurg",
    "Office": "KUDAL",
    "FPS_Id": " 152907100087",
    "RC_Id": " 272013092054",
    "MemberId": " 27201309205401",
    "MemberName": "SATYVATI BABURAO GOVERKAR",
    "Gender": "Female",
    "UID": "XXXX-XXXX-3214",
    "Scheme Type": "NFSA",
    "Scheme": "PHH"
  },
  {
    "SrNo": 79262,
    "District": "Sindhudurg",
    "Office": "KUDAL",
    "FPS_Id": " 152907100087",
    "RC_Id": " 272013092056",
    "MemberId": " 27201309205601",
    "MemberName": "VASANT ganu aair",
    "Gender": "Male",
    "Scheme Type": "NFSA",
    "Scheme": "PHH"
  },
  {
    "SrNo": 79263,
    "District": "Sindhudurg",
    "Office": "KUDAL",
    "FPS_Id": " 152907100087",
    "RC_Id": " 272013092056",
    "MemberId": " 27201309205603",
    "MemberName": "PRAVIN vasant aair",
    "Gender": "Male",
    "Scheme Type": "NFSA",
    "Scheme": "PHH"
  },
  {
    "SrNo": 79264,
    "District": "Sindhudurg",
    "Office": "KUDAL",
    "FPS_Id": " 152907100087",
    "RC_Id": " 272013092060",
    "MemberId": " 27201309206003",
    "MemberName": "SHRADDHA SUBHASHCHANDRA GAWDE",
    "Gender": "Female",
    "Scheme Type": "NFSA",
    "Scheme": "PHH"
  },
  {
    "SrNo": 79265,
    "District": "Sindhudurg",
    "Office": "KUDAL",
    "FPS_Id": " 152907100087",
    "RC_Id": " 272013092060",
    "MemberId": " 27201309206004",
    "MemberName": "VIDYA SUBHASHCHANDRA GAWDE",
    "Gender": "Female",
    "Scheme Type": "NFSA",
    "Scheme": "PHH"
  },
  {
    "SrNo": 79266,
    "District": "Sindhudurg",
    "Office": "KUDAL",
    "FPS_Id": " 152907100087",
    "RC_Id": " 272013092061",
    "MemberId": " 27201309206102",
    "MemberName": "VIJAY GOVIND SHIRKE",
    "Gender": "Male",
    "Scheme Type": "NFSA",
    "Scheme": "PHH"
  },
  {
    "SrNo": 79267,
    "District": "Sindhudurg",
    "Office": "KUDAL",
    "FPS_Id": " 152907100087",
    "RC_Id": " 272013092063",
    "MemberId": " 27201309206301",
    "MemberName": "GOVIND ramkrishna SHETaYE",
    "Gender": "Male",
    "UID": "XXXX-XXXX-3144",
    "Scheme Type": "NFSA",
    "Scheme": "PHH"
  },
  {
    "SrNo": 79268,
    "District": "Sindhudurg",
    "Office": "KUDAL",
    "FPS_Id": " 152907100087",
    "RC_Id": " 272013092064",
    "MemberId": " 27201309206404",
    "MemberName": "PILAJI laxman chavan",
    "Gender": "Male",
    "UID": "XXXX-XXXX-7728",
    "Scheme Type": "NFSA",
    "Scheme": "PHH"
  },
  {
    "SrNo": 79269,
    "District": "Sindhudurg",
    "Office": "KUDAL",
    "FPS_Id": " 152907100087",
    "RC_Id": " 272013092064",
    "MemberId": " 27201309206406",
    "MemberName": "PAYAL PILAJI CHAVAN",
    "Gender": "Female",
    "Scheme Type": "NFSA",
    "Scheme": "PHH"
  },
  {
    "SrNo": 79270,
    "District": "Sindhudurg",
    "Office": "KUDAL",
    "FPS_Id": " 152907100087",
    "RC_Id": " 272013092064",
    "MemberId": " 27201309206407",
    "MemberName": "VAISHANAVI PILAJI CHAVAN",
    "Gender": "Female",
    "Scheme Type": "NFSA",
    "Scheme": "PHH"
  },
  {
    "SrNo": 79271,
    "District": "Sindhudurg",
    "Office": "KUDAL",
    "FPS_Id": " 152907100087",
    "RC_Id": " 272013092067",
    "MemberId": " 27201309206702",
    "MemberName": "SATYAVATI shivram SADVELKAR",
    "Gender": "Female",
    "UID": "XXXX-XXXX-4530",
    "Scheme Type": "NFSA",
    "Scheme": "PHH"
  },
  {
    "SrNo": 79272,
    "District": "Sindhudurg",
    "Office": "KUDAL",
    "FPS_Id": " 152907100087",
    "RC_Id": " 272013092067",
    "MemberId": " 27201309206703",
    "MemberName": "VILAS shivram SADVELKAR",
    "Gender": "Male",
    "UID": "XXXX-XXXX-5687",
    "Scheme Type": "NFSA",
    "Scheme": "PHH"
  },
  {
    "SrNo": 79273,
    "District": "Sindhudurg",
    "Office": "KUDAL",
    "FPS_Id": " 152907100087",
    "RC_Id": " 272013092069",
    "MemberId": " 27201309206901",
    "MemberName": "TUKARAM AAIER",
    "Gender": "Male",
    "UID": "XXXX-XXXX-4599",
    "Scheme Type": "NFSA",
    "Scheme": "PHH"
  },
  {
    "SrNo": 79274,
    "District": "Sindhudurg",
    "Office": "KUDAL",
    "FPS_Id": " 152907100087",
    "RC_Id": " 272013092069",
    "MemberId": " 27201309206904",
    "MemberName": "SITARAM AAIER",
    "Gender": "Male",
    "Scheme Type": "NFSA",
    "Scheme": "PHH"
  },
  {
    "SrNo": 79275,
    "District": "Sindhudurg",
    "Office": "KUDAL",
    "FPS_Id": " 152907100087",
    "RC_Id": " 272013092069",
    "MemberId": " 27201309206906",
    "MemberName": "SUVARNA AAIER",
    "Gender": "Female",
    "Scheme Type": "NFSA",
    "Scheme": "PHH"
  },
  {
    "SrNo": 79276,
    "District": "Sindhudurg",
    "Office": "KUDAL",
    "FPS_Id": " 152907100087",
    "RC_Id": " 272013092069",
    "MemberId": " 27201309206910",
    "MemberName": "RUPESH AAIER",
    "Gender": "Male",
    "Scheme Type": "NFSA",
    "Scheme": "PHH"
  },
  {
    "SrNo": 79277,
    "District": "Sindhudurg",
    "Office": "KUDAL",
    "FPS_Id": " 152907100087",
    "RC_Id": " 272013092069",
    "MemberId": " 27201309206911",
    "MemberName": "GAURAV AAIER",
    "Gender": "Male",
    "Scheme Type": "NFSA",
    "Scheme": "PHH"
  },
  {
    "SrNo": 79278,
    "District": "Sindhudurg",
    "Office": "KUDAL",
    "FPS_Id": " 152907100087",
    "RC_Id": " 272013092074",
    "MemberId": " 27201309207403",
    "MemberName": "DHAKU VARAK",
    "Gender": "Male",
    "Scheme Type": "NFSA",
    "Scheme": "PHH"
  },
  {
    "SrNo": 79279,
    "District": "Sindhudurg",
    "Office": "KUDAL",
    "FPS_Id": " 152907100087",
    "RC_Id": " 272013092074",
    "MemberId": " 27201309207404",
    "MemberName": "MANDA gangaram VARAK",
    "Gender": "Female",
    "Scheme Type": "NFSA",
    "Scheme": "PHH"
  },
  {
    "SrNo": 79280,
    "District": "Sindhudurg",
    "Office": "KUDAL",
    "FPS_Id": " 152907100087",
    "RC_Id": " 272013092074",
    "MemberId": " 27201309207407",
    "MemberName": "savita gangaram varak",
    "Gender": "Female",
    "UID": "XXXX-XXXX-0619",
    "Scheme Type": "NFSA",
    "Scheme": "PHH"
  },
  {
    "SrNo": 79281,
    "District": "Sindhudurg",
    "Office": "KUDAL",
    "FPS_Id": " 152907100087",
    "RC_Id": " 272013092074",
    "MemberId": " 27201309207409",
    "MemberName": "SUNITA VARAK",
    "Gender": "Female",
    "Scheme Type": "NFSA",
    "Scheme": "PHH"
  },
  {
    "SrNo": 79282,
    "District": "Sindhudurg",
    "Office": "KUDAL",
    "FPS_Id": " 152907100087",
    "RC_Id": " 272013092074",
    "MemberId": " 27201309207410",
    "MemberName": "MANDAR VARAK",
    "Gender": "Male",
    "Scheme Type": "NFSA",
    "Scheme": "PHH"
  },
  {
    "SrNo": 79283,
    "District": "Sindhudurg",
    "Office": "KUDAL",
    "FPS_Id": " 152907100087",
    "RC_Id": " 272013092075",
    "MemberId": " 27201309207501",
    "MemberName": "JAYRAM KOLEKAR",
    "Gender": "Male",
    "UID": "XXXX-XXXX-8372",
    "Scheme Type": "NFSA",
    "Scheme": "PHH"
  },
  {
    "SrNo": 79284,
    "District": "Sindhudurg",
    "Office": "KUDAL",
    "FPS_Id": " 152907100087",
    "RC_Id": " 272013092075",
    "MemberId": " 27201309207504",
    "MemberName": "VITTHAL KOLEKAR",
    "Gender": "Male",
    "UID": "XXXX-XXXX-1838",
    "Scheme Type": "NFSA",
    "Scheme": "PHH"
  },
  {
    "SrNo": 79285,
    "District": "Sindhudurg",
    "Office": "KUDAL",
    "FPS_Id": " 152907100087",
    "RC_Id": " 272013092075",
    "MemberId": " 27201309207505",
    "MemberName": "ANUSHRI ANKUSH KOLEKAR",
    "Gender": "Female",
    "Scheme Type": "NFSA",
    "Scheme": "PHH"
  },
  {
    "SrNo": 79286,
    "District": "Sindhudurg",
    "Office": "KUDAL",
    "FPS_Id": " 152907100087",
    "RC_Id": " 272013092076",
    "MemberId": " 27201309207602",
    "MemberName": "suhasini daji aier",
    "Gender": "Female",
    "UID": "XXXX-XXXX-7838",
    "Scheme Type": "NFSA",
    "Scheme": "PHH"
  },
  {
    "SrNo": 79287,
    "District": "Sindhudurg",
    "Office": "KUDAL",
    "FPS_Id": " 152907100087",
    "RC_Id": " 272013092081",
    "MemberId": " 27201309208108",
    "MemberName": "JANHAVI SACHIN MARATHE",
    "Gender": "Female",
    "Scheme Type": "NFSA",
    "Scheme": "PHH"
  },
  {
    "SrNo": 79288,
    "District": "Sindhudurg",
    "Office": "KUDAL",
    "FPS_Id": " 152907100087",
    "RC_Id": " 272013092085",
    "MemberId": " 27201309208507",
    "MemberName": "ARATI SAGAR GOVEKAR",
    "Gender": "Female",
    "UID": "XXXX-XXXX-4423",
    "Scheme Type": "NFSA",
    "Scheme": "PHH"
  },
  {
    "SrNo": 79289,
    "District": "Sindhudurg",
    "Office": "KUDAL",
    "FPS_Id": " 152907100087",
    "RC_Id": " 272013092089",
    "MemberId": " 27201309208905",
    "MemberName": "TEJAS KANU SHELKE",
    "Gender": "Male",
    "UID": "XXXX-XXXX-3219",
    "Scheme Type": "NFSA",
    "Scheme": "PHH"
  },
  {
    "SrNo": 79290,
    "District": "Sindhudurg",
    "Office": "KUDAL",
    "FPS_Id": " 152907100087",
    "RC_Id": " 272013092092",
    "MemberId": " 27201309209201",
    "MemberName": "GANPAT PATKAR",
    "Gender": "Male",
    "Scheme Type": "NFSA",
    "Scheme": "PHH"
  },
  {
    "SrNo": 79291,
    "District": "Sindhudurg",
    "Office": "KUDAL",
    "FPS_Id": " 152907100087",
    "RC_Id": " 272013092092",
    "MemberId": " 27201309209202",
    "MemberName": "MAHESH PATKAR",
    "Gender": "Male",
    "Scheme Type": "NFSA",
    "Scheme": "PHH"
  },
  {
    "SrNo": 79292,
    "District": "Sindhudurg",
    "Office": "KUDAL",
    "FPS_Id": " 152907100087",
    "RC_Id": " 272013092092",
    "MemberId": " 27201309209203",
    "MemberName": "JAYVANTI PATKAR",
    "Gender": "Female",
    "UID": "XXXX-XXXX-7000",
    "Scheme Type": "NFSA",
    "Scheme": "PHH"
  },
  {
    "SrNo": 79293,
    "District": "Sindhudurg",
    "Office": "KUDAL",
    "FPS_Id": " 152907100087",
    "RC_Id": " 272013092092",
    "MemberId": " 27201309209207",
    "MemberName": "MAHESH LAXMAN PATKAR",
    "Gender": "Male",
    "Scheme Type": "NFSA",
    "Scheme": "PHH"
  },
  {
    "SrNo": 79294,
    "District": "Sindhudurg",
    "Office": "KUDAL",
    "FPS_Id": " 152907100087",
    "RC_Id": " 272013092092",
    "MemberId": " 27201309209208",
    "MemberName": "TENDULKAR VISHAKHA YASHAVANT",
    "Gender": "Female",
    "Scheme Type": "NFSA",
    "Scheme": "PHH"
  },
  {
    "SrNo": 79295,
    "District": "Sindhudurg",
    "Office": "KUDAL",
    "FPS_Id": " 152907100087",
    "RC_Id": " 272013092092",
    "MemberId": " 27201309209209",
    "MemberName": "TENDULKAR DIPIKA YASHAVANT",
    "Gender": "Female",
    "Scheme Type": "NFSA",
    "Scheme": "PHH"
  },
  {
    "SrNo": 79296,
    "District": "Sindhudurg",
    "Office": "KUDAL",
    "FPS_Id": " 152907100087",
    "RC_Id": " 272013092095",
    "MemberId": " 27201309209505",
    "MemberName": "KAMALABAI bhagwan BIRMOLE",
    "Gender": "Female",
    "Scheme Type": "NFSA",
    "Scheme": "PHH"
  },
  {
    "SrNo": 79297,
    "District": "Sindhudurg",
    "Office": "KUDAL",
    "FPS_Id": " 152907100087",
    "RC_Id": " 272013092096",
    "MemberId": " 27201309209605",
    "MemberName": "VAISHALI NAIK",
    "Gender": "Female",
    "Scheme Type": "NFSA",
    "Scheme": "PHH"
  },
  {
    "SrNo": 79298,
    "District": "Sindhudurg",
    "Office": "KUDAL",
    "FPS_Id": " 152907100087",
    "RC_Id": " 272013092100",
    "MemberId": " 27201309210001",
    "MemberName": "VASUDEV SHANKAR GORULE",
    "Gender": "Male",
    "UID": "XXXX-XXXX-5982",
    "Scheme Type": "NFSA",
    "Scheme": "PHH"
  },
  {
    "SrNo": 79299,
    "District": "Sindhudurg",
    "Office": "KUDAL",
    "FPS_Id": " 152907100087",
    "RC_Id": " 272013092101",
    "MemberId": " 27201309210103",
    "MemberName": "SANCHITA WAMAN GAWADE",
    "Gender": "Female",
    "UID": "XXXX-XXXX-9364",
    "Scheme Type": "NFSA",
    "Scheme": "PHH"
  },
  {
    "SrNo": 79300,
    "District": "Sindhudurg",
    "Office": "KUDAL",
    "FPS_Id": " 152907100087",
    "RC_Id": " 272013092101",
    "MemberId": " 27201309210104",
    "MemberName": "VAIBHAVI waman GAVADE",
    "Gender": "Female",
    "UID": "XXXX-XXXX-1965",
    "Scheme Type": "NFSA",
    "Scheme": "PHH"
  },
  {
    "SrNo": 79301,
    "District": "Sindhudurg",
    "Office": "KUDAL",
    "FPS_Id": " 152907100087",
    "RC_Id": " 272013092101",
    "MemberId": " 27201309210105",
    "MemberName": "SADHANA waman GAVADE",
    "Gender": "Female",
    "UID": "XXXX-XXXX-5963",
    "Scheme Type": "NFSA",
    "Scheme": "PHH"
  },
  {
    "SrNo": 79302,
    "District": "Sindhudurg",
    "Office": "KUDAL",
    "FPS_Id": " 152907100087",
    "RC_Id": " 272013092101",
    "MemberId": " 27201309210106",
    "MemberName": "SAJUBAI vaman GAVADE",
    "Gender": "Female",
    "UID": "XXXX-XXXX-2277",
    "Scheme Type": "NFSA",
    "Scheme": "PHH"
  },
  {
    "SrNo": 79303,
    "District": "Sindhudurg",
    "Office": "KUDAL",
    "FPS_Id": " 152907100087",
    "RC_Id": " 272013092101",
    "MemberId": " 27201309210107",
    "MemberName": "SANCHITA waman GAVADE",
    "Gender": "Female",
    "Scheme Type": "NFSA",
    "Scheme": "PHH"
  },
  {
    "SrNo": 79304,
    "District": "Sindhudurg",
    "Office": "KUDAL",
    "FPS_Id": " 152907100087",
    "RC_Id": " 272013092101",
    "MemberId": " 27201309210109",
    "MemberName": "GURUNATH GAVADE",
    "Gender": "Male",
    "Scheme Type": "NFSA",
    "Scheme": "PHH"
  },
  {
    "SrNo": 79305,
    "District": "Sindhudurg",
    "Office": "KUDAL",
    "FPS_Id": " 152907100087",
    "RC_Id": " 272013092104",
    "MemberId": " 27201309210403",
    "MemberName": "JANU VARAK",
    "Gender": "Male",
    "Scheme Type": "NFSA",
    "Scheme": "AAY"
  },
  {
    "SrNo": 79306,
    "District": "Sindhudurg",
    "Office": "KUDAL",
    "FPS_Id": " 152907100087",
    "RC_Id": " 272013092104",
    "MemberId": " 27201309210404",
    "MemberName": "JAYASHRI VARAK",
    "Gender": "Female",
    "Scheme Type": "NFSA",
    "Scheme": "AAY"
  },
  {
    "SrNo": 79307,
    "District": "Sindhudurg",
    "Office": "KUDAL",
    "FPS_Id": " 152907100087",
    "RC_Id": " 272013092104",
    "MemberId": " 27201309210406",
    "MemberName": "VIJAY VARAK",
    "Gender": "Male",
    "Scheme Type": "NFSA",
    "Scheme": "AAY"
  },
  {
    "SrNo": 79308,
    "District": "Sindhudurg",
    "Office": "KUDAL",
    "FPS_Id": " 152907100087",
    "RC_Id": " 272013092104",
    "MemberId": " 27201309210407",
    "MemberName": "VEESHNVI VARAK",
    "Gender": "Female",
    "Scheme Type": "NFSA",
    "Scheme": "AAY"
  },
  {
    "SrNo": 79309,
    "District": "Sindhudurg",
    "Office": "KUDAL",
    "FPS_Id": " 152907100087",
    "RC_Id": " 272013092105",
    "MemberId": " 27201309210508",
    "MemberName": "MAYURI RAJAN GORULE",
    "Gender": "Female",
    "UID": "XXXX-XXXX-1494",
    "Scheme Type": "NFSA",
    "Scheme": "PHH"
  },
  {
    "SrNo": 79310,
    "District": "Sindhudurg",
    "Office": "KUDAL",
    "FPS_Id": " 152907100087",
    "RC_Id": " 272013092115",
    "MemberId": " 27201309211501",
    "MemberName": "SOMA vaman MARGAJ",
    "Gender": "Male",
    "UID": "XXXX-XXXX-3998",
    "Scheme Type": "NFSA",
    "Scheme": "PHH"
  },
  {
    "SrNo": 79311,
    "District": "Sindhudurg",
    "Office": "KUDAL",
    "FPS_Id": " 152907100087",
    "RC_Id": " 272013092115",
    "MemberId": " 27201309211503",
    "MemberName": "NISHA soma MARGAJ",
    "Gender": "Female",
    "Scheme Type": "NFSA",
    "Scheme": "PHH"
  },
  {
    "SrNo": 79312,
    "District": "Sindhudurg",
    "Office": "KUDAL",
    "FPS_Id": " 152907100087",
    "RC_Id": " 272013092115",
    "MemberId": " 27201309211505",
    "MemberName": "VAMAN soma MARGAJ",
    "Gender": "Male",
    "UID": "XXXX-XXXX-8919",
    "Scheme Type": "NFSA",
    "Scheme": "PHH"
  },
  {
    "SrNo": 79313,
    "District": "Sindhudurg",
    "Office": "KUDAL",
    "FPS_Id": " 152907100087",
    "RC_Id": " 272013092115",
    "MemberId": " 27201309211506",
    "MemberName": "URMILA vaman MARGAJ",
    "Gender": "Female",
    "UID": "XXXX-XXXX-1082",
    "Scheme Type": "NFSA",
    "Scheme": "PHH"
  },
  {
    "SrNo": 79314,
    "District": "Sindhudurg",
    "Office": "KUDAL",
    "FPS_Id": " 152907100087",
    "RC_Id": " 272013092115",
    "MemberId": " 27201309211507",
    "MemberName": "NAMRATA vaman MARGAJ",
    "Gender": "Female",
    "Scheme Type": "NFSA",
    "Scheme": "PHH"
  },
  {
    "SrNo": 79315,
    "District": "Sindhudurg",
    "Office": "KUDAL",
    "FPS_Id": " 152907100087",
    "RC_Id": " 272013092115",
    "MemberId": " 27201309211508",
    "MemberName": "SNEHA vaman MARGAJ",
    "Gender": "Female",
    "UID": "XXXX-XXXX-0959",
    "Scheme Type": "NFSA",
    "Scheme": "PHH"
  },
  {
    "SrNo": 79316,
    "District": "Sindhudurg",
    "Office": "KUDAL",
    "FPS_Id": " 152907100087",
    "RC_Id": " 272013092115",
    "MemberId": " 27201309211509",
    "MemberName": "NUTAN VAMAN MERGAJ",
    "Gender": "Female",
    "UID": "XXXX-XXXX-3343",
    "Scheme Type": "NFSA",
    "Scheme": "PHH"
  },
  {
    "SrNo": 79317,
    "District": "Sindhudurg",
    "Office": "KUDAL",
    "FPS_Id": " 152907100087",
    "RC_Id": " 272013092117",
    "MemberId": " 27201309211701",
    "MemberName": "EKNATH CHAVAN",
    "Gender": "Male",
    "UID": "XXXX-XXXX-7427",
    "Scheme Type": "NFSA",
    "Scheme": "PHH"
  },
  {
    "SrNo": 79318,
    "District": "Sindhudurg",
    "Office": "KUDAL",
    "FPS_Id": " 152907100087",
    "RC_Id": " 272013092117",
    "MemberId": " 27201309211702",
    "MemberName": "SUVARNA CHAVAN",
    "Gender": "Female",
    "UID": "XXXX-XXXX-0037",
    "Scheme Type": "NFSA",
    "Scheme": "PHH"
  },
  {
    "SrNo": 79319,
    "District": "Sindhudurg",
    "Office": "KUDAL",
    "FPS_Id": " 152907100087",
    "RC_Id": " 272013092117",
    "MemberId": " 27201309211703",
    "MemberName": "SONAM CHAVAN",
    "Gender": "Female",
    "Scheme Type": "NFSA",
    "Scheme": "PHH"
  },
  {
    "SrNo": 79320,
    "District": "Sindhudurg",
    "Office": "KUDAL",
    "FPS_Id": " 152907100087",
    "RC_Id": " 272013092121",
    "MemberId": " 27201309212106",
    "MemberName": "SHON TAMAS SOJ",
    "Gender": "Male",
    "Scheme Type": "NFSA",
    "Scheme": "PHH"
  },
  {
    "SrNo": 79321,
    "District": "Sindhudurg",
    "Office": "KUDAL",
    "FPS_Id": " 152907100087",
    "RC_Id": " 272013092125",
    "MemberId": " 27201309212501",
    "MemberName": "SUMITRA chandrakant MANJAREKAR",
    "Gender": "Female",
    "UID": "XXXX-XXXX-6402",
    "Scheme Type": "NFSA",
    "Scheme": "PHH"
  },
  {
    "SrNo": 79322,
    "District": "Sindhudurg",
    "Office": "KUDAL",
    "FPS_Id": " 152907100087",
    "RC_Id": " 272013092125",
    "MemberId": " 27201309212502",
    "MemberName": "CHANDRAKANT mahadev MANJAREKAR",
    "Gender": "Male",
    "UID": "XXXX-XXXX-8584",
    "Scheme Type": "NFSA",
    "Scheme": "PHH"
  },
  {
    "SrNo": 79323,
    "District": "Sindhudurg",
    "Office": "KUDAL",
    "FPS_Id": " 152907100087",
    "RC_Id": " 272013092125",
    "MemberId": " 27201309212505",
    "MemberName": "ULKA ulhas MANJAREKAR",
    "Gender": "Female",
    "UID": "XXXX-XXXX-1808",
    "Scheme Type": "NFSA",
    "Scheme": "PHH"
  },
  {
    "SrNo": 79324,
    "District": "Sindhudurg",
    "Office": "KUDAL",
    "FPS_Id": " 152907100087",
    "RC_Id": " 272013092125",
    "MemberId": " 27201309212506",
    "MemberName": "AKANKSHA akash MANJAREKAR",
    "Gender": "Female",
    "UID": "XXXX-XXXX-8753",
    "Scheme Type": "NFSA",
    "Scheme": "PHH"
  },
  {
    "SrNo": 79325,
    "District": "Sindhudurg",
    "Office": "KUDAL",
    "FPS_Id": " 152907100087",
    "RC_Id": " 272013092125",
    "MemberId": " 27201309212507",
    "MemberName": "mayuri uLhas manjarekar",
    "Gender": "Female",
    "UID": "XXXX-XXXX-2310",
    "Scheme Type": "NFSA",
    "Scheme": "PHH"
  },
  {
    "SrNo": 79326,
    "District": "Sindhudurg",
    "Office": "KUDAL",
    "FPS_Id": " 152907100087",
    "RC_Id": " 272013092125",
    "MemberId": " 27201309212508",
    "MemberName": "PRAJAKTA ULHAS MANJAREKAR",
    "Gender": "Female",
    "UID": "XXXX-XXXX-6034",
    "Scheme Type": "NFSA",
    "Scheme": "PHH"
  },
  {
    "SrNo": 79327,
    "District": "Sindhudurg",
    "Office": "KUDAL",
    "FPS_Id": " 152907100087",
    "RC_Id": " 272013092125",
    "MemberId": " 27201309212509",
    "MemberName": "OMKAR ULHAS MANJAREKAR",
    "Gender": "Male",
    "UID": "XXXX-XXXX-7838",
    "Scheme Type": "NFSA",
    "Scheme": "PHH"
  },
  {
    "SrNo": 79328,
    "District": "Sindhudurg",
    "Office": "KUDAL",
    "FPS_Id": " 152907100087",
    "RC_Id": " 272013092134",
    "MemberId": " 27201309213401",
    "MemberName": "YASHODA GAVADE",
    "Gender": "Female",
    "UID": "XXXX-XXXX-2764",
    "Scheme Type": "NFSA",
    "Scheme": "PHH"
  },
  {
    "SrNo": 79329,
    "District": "Sindhudurg",
    "Office": "KUDAL",
    "FPS_Id": " 152907100087",
    "RC_Id": " 272013092151",
    "MemberId": " 27201309215104",
    "MemberName": "SUCHITA KRUSHNA CHAVAN",
    "Gender": "Female",
    "UID": "XXXX-XXXX-5898",
    "Scheme Type": "NFSA",
    "Scheme": "PHH"
  },
  {
    "SrNo": 79330,
    "District": "Sindhudurg",
    "Office": "KUDAL",
    "FPS_Id": " 152907100087",
    "RC_Id": " 272013092264",
    "MemberId": " 27201309226401",
    "MemberName": "BABURAV KOLEKAR",
    "Gender": "Male",
    "Scheme Type": "NFSA",
    "Scheme": "PHH"
  },
  {
    "SrNo": 79331,
    "District": "Sindhudurg",
    "Office": "KUDAL",
    "FPS_Id": " 152907100087",
    "RC_Id": " 272013092265",
    "MemberId": " 27201309226501",
    "MemberName": "BALIRAM JADHAV",
    "Gender": "Male",
    "UID": "XXXX-XXXX-7531",
    "Scheme Type": "NFSA",
    "Scheme": "PHH"
  },
  {
    "SrNo": 79332,
    "District": "Sindhudurg",
    "Office": "KUDAL",
    "FPS_Id": " 152907100087",
    "RC_Id": " 272013092284",
    "MemberId": " 27201309228401",
    "MemberName": "SANJAY madhukar GOVEKAR",
    "Gender": "Male",
    "UID": "XXXX-XXXX-3346",
    "Scheme Type": "NFSA",
    "Scheme": "PHH"
  },
  {
    "SrNo": 79333,
    "District": "Sindhudurg",
    "Office": "KUDAL",
    "FPS_Id": " 152907100087",
    "RC_Id": " 272013092284",
    "MemberId": " 27201309228404",
    "MemberName": "SURENDRA sanjay GOVEKAR",
    "Gender": "Male",
    "UID": "XXXX-XXXX-0217",
    "Scheme Type": "NFSA",
    "Scheme": "PHH"
  },
  {
    "SrNo": 79334,
    "District": "Sindhudurg",
    "Office": "KUDAL",
    "FPS_Id": " 152907100087",
    "RC_Id": " 272013092393",
    "MemberId": " 27201309239305",
    "MemberName": "NAYANA BIRU KOLEKAR",
    "Gender": "Female",
    "UID": "XXXX-XXXX-5703",
    "Scheme Type": "NFSA",
    "Scheme": "PHH"
  },
  {
    "SrNo": 79335,
    "District": "Sindhudurg",
    "Office": "KUDAL",
    "FPS_Id": " 152907100087",
    "RC_Id": " 272013092395",
    "MemberId": " 27201309239503",
    "MemberName": "DATTATRAY NARAYAN CHAVAN",
    "Gender": "Male",
    "UID": "XXXX-XXXX-4935",
    "Scheme Type": "NFSA",
    "Scheme": "PHH"
  },
  {
    "SrNo": 79336,
    "District": "Sindhudurg",
    "Office": "KUDAL",
    "FPS_Id": " 152907100087",
    "RC_Id": " 272013092396",
    "MemberId": " 27201309239603",
    "MemberName": "DISHA rajesh RANE",
    "Gender": "Female",
    "Scheme Type": "NFSA",
    "Scheme": "PHH"
  },
  {
    "SrNo": 79337,
    "District": "Sindhudurg",
    "Office": "KUDAL",
    "FPS_Id": " 152907100087",
    "RC_Id": " 272013092396",
    "MemberId": " 27201309239605",
    "MemberName": "PALLAVI SATISH RANE",
    "Gender": "Female",
    "UID": "XXXX-XXXX-3991",
    "Scheme Type": "NFSA",
    "Scheme": "PHH"
  },
  {
    "SrNo": 79338,
    "District": "Sindhudurg",
    "Office": "KUDAL",
    "FPS_Id": " 152907100087",
    "RC_Id": " 272013092396",
    "MemberId": " 27201309239606",
    "MemberName": "ISHAAN SATISH RANE",
    "Gender": "Male",
    "UID": "XXXX-XXXX-7600",
    "Scheme Type": "NFSA",
    "Scheme": "PHH"
  },
  {
    "SrNo": 79339,
    "District": "Sindhudurg",
    "Office": "KUDAL",
    "FPS_Id": " 152907100087",
    "RC_Id": " 272013092397",
    "MemberId": " 27201309239702",
    "MemberName": "SUSHAMA DIGE",
    "Gender": "Female",
    "UID": "XXXX-XXXX-3685",
    "Scheme Type": "NFSA",
    "Scheme": "PHH"
  },
  {
    "SrNo": 79340,
    "District": "Sindhudurg",
    "Office": "KUDAL",
    "FPS_Id": " 152907100087",
    "RC_Id": " 272013092401",
    "MemberId": " 27201309240103",
    "MemberName": "ARCHANA ravindra GAWADE",
    "Gender": "Female",
    "UID": "XXXX-XXXX-7605",
    "Scheme Type": "NFSA",
    "Scheme": "PHH"
  },
  {
    "SrNo": 79341,
    "District": "Sindhudurg",
    "Office": "KUDAL",
    "FPS_Id": " 152907100087",
    "RC_Id": " 272013092402",
    "MemberId": " 27201309240205",
    "MemberName": "SANGITA BAPU BUTE",
    "Gender": "Female",
    "Scheme Type": "NFSA",
    "Scheme": "PHH"
  },
  {
    "SrNo": 79342,
    "District": "Sindhudurg",
    "Office": "KUDAL",
    "FPS_Id": " 152907100087",
    "RC_Id": " 272013092408",
    "MemberId": " 27201309240805",
    "MemberName": "SWARA PRASAD KADAM",
    "Gender": "Female",
    "UID": "XXXX-XXXX-8680",
    "Scheme Type": "NFSA",
    "Scheme": "PHH"
  },
  {
    "SrNo": 79343,
    "District": "Sindhudurg",
    "Office": "KUDAL",
    "FPS_Id": " 152907100087",
    "RC_Id": " 272013092408",
    "MemberId": " 27201309240806",
    "MemberName": "SRUSHTI PRASAD KADAM",
    "Gender": "Female",
    "UID": "XXXX-XXXX-7389",
    "Scheme Type": "NFSA",
    "Scheme": "PHH"
  },
  {
    "SrNo": 79344,
    "District": "Sindhudurg",
    "Office": "KUDAL",
    "FPS_Id": " 152907100087",
    "RC_Id": " 272013092410",
    "MemberId": " 27201309241005",
    "MemberName": "MAHESH MADHUKAR GORULE",
    "Gender": "Male",
    "UID": "XXXX-XXXX-7006",
    "Scheme Type": "NFSA",
    "Scheme": "PHH"
  },
  {
    "SrNo": 79345,
    "District": "Sindhudurg",
    "Office": "KUDAL",
    "FPS_Id": " 152907100087",
    "RC_Id": " 272013092410",
    "MemberId": " 27201309241007",
    "MemberName": "SIDDHI MAHESH GORULE",
    "Gender": "Female",
    "UID": "XXXX-XXXX-9551",
    "Scheme Type": "NFSA",
    "Scheme": "PHH"
  },
  {
    "SrNo": 79346,
    "District": "Sindhudurg",
    "Office": "KUDAL",
    "FPS_Id": " 152907100087",
    "RC_Id": " 272013093678",
    "MemberId": " 27201309367806",
    "MemberName": "VILAS RAMKRISHNA SHETYE",
    "Gender": "Male",
    "UID": "XXXX-XXXX-4923",
    "Scheme Type": "NFSA",
    "Scheme": "PHH"
  },
  {
    "SrNo": 79347,
    "District": "Sindhudurg",
    "Office": "KUDAL",
    "FPS_Id": " 152907100087",
    "RC_Id": " 272013098567",
    "MemberId": " 27201309856701",
    "MemberName": "MORYE KAMALA",
    "Gender": "Female",
    "Scheme Type": "NFSA",
    "Scheme": "PHH"
  },
  {
    "SrNo": 79348,
    "District": "Sindhudurg",
    "Office": "KUDAL",
    "FPS_Id": " 152907100087",
    "RC_Id": " 272013099349",
    "MemberId": " 27201309934901",
    "MemberName": "NANDKISHORE SALSKAR",
    "Gender": "Male",
    "Scheme Type": "NFSA",
    "Scheme": "PHH"
  },
  {
    "SrNo": 79349,
    "District": "Sindhudurg",
    "Office": "KUDAL",
    "FPS_Id": " 152907100087",
    "RC_Id": " 272013099669",
    "MemberId": " 27201309966901",
    "MemberName": "DILIP GADEKAR",
    "Gender": "Male",
    "Scheme Type": "NFSA",
    "Scheme": "AAY"
  },
  {
    "SrNo": 79350,
    "District": "Sindhudurg",
    "Office": "KUDAL",
    "FPS_Id": " 152907100087",
    "RC_Id": " 272013099686",
    "MemberId": " 27201309968601",
    "MemberName": "SURESH NAIK",
    "Gender": "Male",
    "Scheme Type": "NFSA",
    "Scheme": "PHH"
  },
  {
    "SrNo": 79351,
    "District": "Sindhudurg",
    "Office": "KUDAL",
    "FPS_Id": " 152907100087",
    "RC_Id": " 272013099736",
    "MemberId": " 27201309973601",
    "MemberName": "SATYAVATI SHEDAGE",
    "Gender": "Female",
    "Scheme Type": "NFSA",
    "Scheme": "PHH"
  },
  {
    "SrNo": 79352,
    "District": "Sindhudurg",
    "Office": "KUDAL",
    "FPS_Id": " 152907100087",
    "RC_Id": " 272013099769",
    "MemberId": " 27201309976901",
    "MemberName": "RAMCHANDRA MADHUKAR THAKAR",
    "Gender": "Male",
    "Scheme Type": "NFSA",
    "Scheme": "PHH"
  },
  {
    "SrNo": 79353,
    "District": "Sindhudurg",
    "Office": "KUDAL",
    "FPS_Id": " 152907100087",
    "RC_Id": " 272013100063",
    "MemberId": " 27201310006301",
    "MemberName": "PATIL SANJAY BALASAHEB",
    "Gender": "Male",
    "Scheme Type": "NFSA",
    "Scheme": "PHH"
  },
  {
    "SrNo": 79354,
    "District": "Sindhudurg",
    "Office": "KUDAL",
    "FPS_Id": " 152907100087",
    "RC_Id": " 272013100076",
    "MemberId": " 27201310007601",
    "MemberName": "SHAILAJA",
    "Gender": "Female",
    "Scheme Type": "NFSA",
    "Scheme": "PHH"
  },
  {
    "SrNo": 79355,
    "District": "Sindhudurg",
    "Office": "KUDAL",
    "FPS_Id": " 152907100087",
    "RC_Id": " 272013118642",
    "MemberId": " 27201311864201",
    "MemberName": "NERURKAR SUSHILA SADANAND",
    "Gender": "Female",
    "Scheme Type": "NFSA",
    "Scheme": "PHH"
  },
  {
    "SrNo": 79356,
    "District": "Sindhudurg",
    "Office": "KUDAL",
    "FPS_Id": " 152907100087",
    "RC_Id": " 272013184825",
    "MemberId": " 27201318482501",
    "MemberName": "GHADIGAVKAR RAJARAM",
    "Gender": "Male",
    "Scheme Type": "NFSA",
    "Scheme": "PHH"
  },
  {
    "SrNo": 79357,
    "District": "Sindhudurg",
    "Office": "KUDAL",
    "FPS_Id": " 152907100087",
    "RC_Id": " 272013184825",
    "MemberId": " 27201318482503",
    "MemberName": "NARAYAN HIRABA AIER",
    "Gender": "Male",
    "UID": "XXXX-XXXX-8935",
    "Scheme Type": "NFSA",
    "Scheme": "PHH"
  },
  {
    "SrNo": 79358,
    "District": "Sindhudurg",
    "Office": "KUDAL",
    "FPS_Id": " 152907100087",
    "RC_Id": " 272013184906",
    "MemberId": " 27201318490601",
    "MemberName": "KHARUDE RENUKA",
    "Gender": "Female",
    "Scheme Type": "NFSA",
    "Scheme": "PHH"
  },
  {
    "SrNo": 79359,
    "District": "Sindhudurg",
    "Office": "KUDAL",
    "FPS_Id": " 152907100087",
    "RC_Id": " 272027148790",
    "MemberId": " 27202714879001",
    "MemberName": "ANITA SURESHCHANDRA GAWADE",
    "Gender": "Female",
    "UID": "XXXX-XXXX-1636",
    "Scheme Type": "NFSA",
    "Scheme": "PHH"
  },
  {
    "SrNo": 79360,
    "District": "Sindhudurg",
    "Office": "KUDAL",
    "FPS_Id": " 152907100087",
    "RC_Id": " 272027360542",
    "MemberId": " 27202736054201",
    "MemberName": "prabhavati motiram gawade",
    "Gender": "Female",
    "UID": "XXXX-XXXX-7020",
    "Scheme Type": "NFSA",
    "Scheme": "PHH"
  },
  {
    "SrNo": 79361,
    "District": "Sindhudurg",
    "Office": "KUDAL",
    "FPS_Id": " 152907100087",
    "RC_Id": " 272027556234",
    "MemberId": " 27202755623403",
    "MemberName": "pragati prakash chavan",
    "Gender": "Female",
    "UID": "XXXX-XXXX-0254",
    "Scheme Type": "NFSA",
    "Scheme": "PHH"
  },
  {
    "SrNo": 79362,
    "District": "Sindhudurg",
    "Office": "KUDAL",
    "FPS_Id": " 152907100087",
    "RC_Id": " 272027599500",
    "MemberId": " 27202759950003",
    "MemberName": "shivani shivaji shelake",
    "Gender": "Female",
    "UID": "XXXX-XXXX-0899",
    "Scheme Type": "NFSA",
    "Scheme": "PHH"
  },
  {
    "SrNo": 79363,
    "District": "Sindhudurg",
    "Office": "KUDAL",
    "FPS_Id": " 152907100087",
    "RC_Id": " 272027636501",
    "MemberId": " 27202763650102",
    "MemberName": "madhukar dhaku parab",
    "Gender": "Male",
    "UID": "XXXX-XXXX-0703",
    "Scheme Type": "NFSA",
    "Scheme": "PHH"
  },
  {
    "SrNo": 79364,
    "District": "Sindhudurg",
    "Office": "KUDAL",
    "FPS_Id": " 152907100087",
    "RC_Id": " 272027636501",
    "MemberId": " 27202763650103",
    "MemberName": "pushparaj madhukar parab",
    "Gender": "Male",
    "UID": "XXXX-XXXX-4431",
    "Scheme Type": "NFSA",
    "Scheme": "PHH"
  },
  {
    "SrNo": 79365,
    "District": "Sindhudurg",
    "Office": "KUDAL",
    "FPS_Id": " 152907100087",
    "RC_Id": " 272027649431",
    "MemberId": " 27202764943104",
    "MemberName": "joyal francis d''souza",
    "Gender": "Male",
    "UID": "XXXX-XXXX-7017",
    "Scheme Type": "NFSA",
    "Scheme": "PHH"
  },
  {
    "SrNo": 79366,
    "District": "Sindhudurg",
    "Office": "KUDAL",
    "FPS_Id": " 152907100087",
    "RC_Id": " 272027911907",
    "MemberId": " 27202791190705",
    "MemberName": "roshan rajendra shelke",
    "Gender": "Male",
    "UID": "XXXX-XXXX-2846",
    "Scheme Type": "NFSA",
    "Scheme": "PHH"
  },
  {
    "SrNo": 79367,
    "District": "Sindhudurg",
    "Office": "KUDAL",
    "FPS_Id": " 152907100087",
    "RC_Id": " 272028474772",
    "MemberId": " 27202847477202",
    "MemberName": "parashuram babu mhapankar",
    "Gender": "Male",
    "UID": "XXXX-XXXX-1129",
    "Scheme Type": "NFSA",
    "Scheme": "PHH"
  },
  {
    "SrNo": 79368,
    "District": "Sindhudurg",
    "Office": "KUDAL",
    "FPS_Id": " 152907100087",
    "RC_Id": " 272028588269",
    "MemberId": " 27202858826903",
    "MemberName": "riya deepak bute",
    "Gender": "Female",
    "UID": "XXXX-XXXX-7665",
    "Scheme Type": "NFSA",
    "Scheme": "PHH"
  },
  {
    "SrNo": 79369,
    "District": "Sindhudurg",
    "Office": "KUDAL",
    "FPS_Id": " 152907100087",
    "RC_Id": " 272031409708",
    "MemberId": " 27203140970803",
    "MemberName": "KRUTIKA SACHIN CHAVAN",
    "Gender": "Female",
    "UID": "XXXX-XXXX-5153",
    "Scheme Type": "NFSA",
    "Scheme": "PHH"
  }
]